[
	{"awareness" : "Website"},
	{"awareness" : "Physical storefront"},
	{"awareness" : "Amazon"},
	{"awareness" : "Google shopping"},
	{"awareness" : "Etsy"},
	{"awareness" : "Articles"},
	{"awareness" : "eBook"},
	{"awareness" : "TV ads"},
	{"awareness" : "Radio ads"},
	{"awareness" : "Podcast ads"},
	{"awareness" : "Online ads"},
	{"awareness" : "Shelf-space in other stores"},
	{"awareness" : "Tradeshows"},
	{"awareness" : "How-to-videos"},
	{"awareness" : "Cross promotion"},
	{"awareness" : "Referrals / word-of-mouth"},
	{"awareness" : "Signage (incl. billboards)"},
	{"awareness" : "Direct mailers"},
	{"awareness" : "Email newsletter"},

	{"evaluation": "Competitive comparison"},
	{"evaluation": "Feature list"},
	{"evaluation": "Data sheet"},
	{"evaluation": "Case study"},
	{"evaluation": "Testimonials"},
	{"evaluation": "Webinar"},
	{"evaluation": "Online reviews"},
	{"evaluation": "FAQ"},
	{"evaluation": "Samples"},
	{"evaluation": "Demo video"},

	{"conversion": "Free trial"},
	{"conversion": "Pricing page"},
	{"conversion": "Live demo"},
	{"conversion": "Consultation"},
	{"conversion": "Estimate / quote"},
	{"conversion": "Coupon"},
	{"conversion": "Call-to-action"},
	{"conversion": "Re-targeting"},
	{"conversion": "Sales call follow-up"},
	{"conversion": "Drip email campaign"},

	{"retention": "Packaging"},
	{"retention": "Email follow-up"},
	{"retention": "Coupons"},
	{"retention": "Subscription"},
	{"retention": "Easy re-order"},
	{"retention": "Birthday gifts"},
	{"retention": "New product notices"},
	{"retention": "Re-targeting online ads"},
	{"retention": "Cross-promotion / nurture campaigns"},
	{"retention": "Perk milestones for subscription anniversaries"},


	{"referral" : "Packaging"},
	{"referral" : "Social sharing incentive"},
	{"referral" : "Shareable coupons"},
	{"referral" : "Referral incentive"},
	{"referral" : "Testimonial / Reviews"},
	{"referral" : "User generated content"}

]